videocv/__init__.py
videocv/__main__.py
videocv/utils.py
videocv/version.py
videocv/video.py
videocv-0.1.7.dist-info/LICENSE
videocv-0.1.7.dist-info/METADATA
videocv-0.1.7.dist-info/WHEEL
videocv-0.1.7.dist-info/top_level.txt
videocv-0.1.7.dist-info/RECORD
