Metadata-Version: 2.1
Name: videocv
Version: 0.1.7
Summary: Video & OpenCV
Home-page: https://github.com/sjjeong94/videocv
Author: sjjeong94
Author-email: sjjeong94@gmail.com
License: MIT
License-File: LICENSE
Requires-Dist: opencv-python
